{
  "project_info": {
    "project_number": "135191614480",
    "project_id": "prime-scheduler-a99ca",
    "storage_bucket": "prime-scheduler-a99ca.appspot.com"
  },
  "client": [
    {
      "client_info": {
        "mobilesdk_app_id": "1:135191614480:android:6ae5cf498f141e2b86a695",
        "android_client_info": {
          "package_name": "com.prime_scheduler"
        }
      },
      "oauth_client": [
        {
          "client_id": "135191614480-d141beed5kfbmppfvh957ispoch5i3lc.apps.googleusercontent.com",
          "client_type": 3
        }
      ],
      "api_key": [
        {
          "current_key": "AIzaSyC28-k89x0V4EEG_vtdbwB3YVnBxQjxrz8"
        }
      ],
      "services": {
        "appinvite_service": {
          "other_platform_oauth_client": [
            {
              "client_id": "135191614480-d141beed5kfbmppfvh957ispoch5i3lc.apps.googleusercontent.com",
              "client_type": 3
            }
          ]
        }
      }
    }
  ],
  "configuration_version": "1"
}